{
  "defaultTitle": "Performance Analytics",
  "granularityInfo": {
    "showing": "Showing",
    "over": "over",
    "days": "days"
  },
  "metrics": {
    "avgGrowth": "Avg Growth",
    "peak": "Peak",
    "current": "Current"
  },
  "autoGranularity": {
    "title": "Auto Granularity",
    "description": "{granularity} breakdown over {days} days"
  },
  "tooltip": {
    "performance": "Performance"
  },
  "loading": {
    "title": "Loading Performance Data...",
    "description": "Please wait while we fetch your analytics"
  },
  "error": {
    "title": "Unable to Load Data",
    "description": "There was an error loading the performance data. Please try again.",
    "retry": "Retry"
  },
  "noData": {
    "title": "No Data Available",
    "description": "No performance data available for the selected time period.",
    "suggestion": "Try selecting a different time range or check your filters."
  }
}